griptape/__init__.py
griptape/tools/__init__.py
griptape/tools/aws_iam_client/__init__.py
griptape/tools/aws_iam_client/manifest.yml
griptape/tools/aws_iam_client/tool.py
griptape/tools/aws_s3_client/__init__.py
griptape/tools/aws_s3_client/manifest.yml
griptape/tools/aws_s3_client/tool.py
griptape/tools/base_aws_client.py
griptape/tools/calculator/__init__.py
griptape/tools/calculator/manifest.yml
griptape/tools/calculator/tool.py
griptape/tools/computer/__init__.py
griptape/tools/computer/manifest.yml
griptape/tools/computer/resources/Dockerfile
griptape/tools/computer/resources/requirements.txt
griptape/tools/computer/tool.py
griptape/tools/date_time/__init__.py
griptape/tools/date_time/manifest.yml
griptape/tools/date_time/tool.py
griptape/tools/email_client/__init__.py
griptape/tools/email_client/manifest.yml
griptape/tools/email_client/requirements.txt
griptape/tools/email_client/tool.py
griptape/tools/file_manager/__init__.py
griptape/tools/file_manager/manifest.yml
griptape/tools/file_manager/tool.py
griptape/tools/knowledge_base_client/__init__.py
griptape/tools/knowledge_base_client/manifest.yml
griptape/tools/knowledge_base_client/requirements.txt
griptape/tools/knowledge_base_client/tool.py
griptape/tools/rest_api_client/__init__.py
griptape/tools/rest_api_client/manifest.yml
griptape/tools/rest_api_client/requirements.txt
griptape/tools/rest_api_client/tool.py
griptape/tools/sql_client/__init__.py
griptape/tools/sql_client/manifest.yml
griptape/tools/sql_client/tool.py
griptape/tools/tool_output_processor/__init__.py
griptape/tools/tool_output_processor/manifest.yml
griptape/tools/tool_output_processor/tool.py
griptape/tools/web_scraper/__init__.py
griptape/tools/web_scraper/manifest.yml
griptape/tools/web_scraper/requirements.txt
griptape/tools/web_scraper/tool.py
griptape/tools/web_search/__init__.py
griptape/tools/web_search/manifest.yml
griptape/tools/web_search/requirements.txt
griptape/tools/web_search/tool.py
griptape_tools-0.16.3.dist-info/LICENSE
griptape_tools-0.16.3.dist-info/METADATA
griptape_tools-0.16.3.dist-info/WHEEL
griptape_tools-0.16.3.dist-info/RECORD
