Metadata-Version: 2.1
Name: griptape-tools
Version: 0.16.3
Summary: Tools for the Griptape framework.
Home-page: https://github.com/griptape-ai/griptape-tools
License: Apache 2.0
Author: Griptape
Author-email: hello@griptape.ai
Requires-Python: >=3.9,<4.0
Classifier: License :: Other/Proprietary License
Classifier: Programming Language :: Python :: 3
Classifier: Programming Language :: Python :: 3.9
Classifier: Programming Language :: Python :: 3.10
Classifier: Programming Language :: Python :: 3.11
Requires-Dist: boto3 (>=1.28.2,<2.0.0)
Requires-Dist: docker (>=6.1.3,<7.0.0)
Requires-Dist: griptape (>=0.14.6)
Requires-Dist: stringcase (>=1.2.0,<2.0.0)
Project-URL: Repository, https://github.com/griptape-ai/griptape-tools
